[[{"__type__":"cc.Prefab","_name":"limit1","data":{"__id__":1}},{"__type__":"cc.Node","_name":"limit1","_children":[{"__id__":2}],"_prefab":{"__type__":"cc.PrefabInfo","root":{"__id__":1},"asset":{"__uuid__":"056TbB+KxLHLTcRpr3gozA"},"fileId":"45fkb01/JDA5tK8/KWI3Xt"},"_contentSize":{"__type__":"cc.Size","width":50,"height":48},"_trs":{"__type__":"TypedArray","ctor":"Float64Array","array":[-166.75,-69.522,0,0,0,0,1,1.2,1.2,1.2]},"_groupIndex":2,"groupIndex":2},{"__type__":"cc.Node","_name":"New Node","_parent":{"__id__":1},"_components":[{"__type__":"cc.Sprite","node":{"__id__":2},"_materials":[{"__uuid__":"ecpdLyjvZBwrvm+cedCcQy"}],"_spriteFrame":{"__uuid__":"59/EP/lllHPpWJmDyWZ59/"}}],"_prefab":{"__type__":"cc.PrefabInfo","root":{"__id__":1},"asset":{"__uuid__":"056TbB+KxLHLTcRpr3gozA"},"fileId":"1acKYb7NtHA4gqPBLFS3Pa"},"_contentSize":{"__type__":"cc.Size","width":162,"height":155},"_trs":{"__type__":"TypedArray","ctor":"Float64Array","array":[0,0,0,0,0,0,1,0.3,0.3,1]},"_groupIndex":2,"groupIndex":2}],{"__type__":"cc.SpriteFrame","content":{"name":"slice211_@","texture":"11c322f24","rect":[1585,199,162,155],"offset":[0,0],"originalSize":[162,155],"rotated":1,"capInsets":[0,0,0,0]}}]